{"width":2048,"imagePath":"dianji1_tex.png","height":1024,"name":"dianji1","SubTexture":[{"y":383,"frameX":-78,"frameHeight":500,"frameY":-68,"width":348,"frameWidth":500,"height":346,"name":"圆环/圆2_0006","x":1377},{"width":500,"y":1,"height":500,"name":"圆环/圆2_0010","x":503},{"y":1,"frameX":-62,"frameHeight":500,"frameY":-51,"width":380,"frameWidth":500,"height":380,"name":"圆环/圆2_0008","x":1005},{"y":731,"frameX":-203,"frameHeight":500,"frameY":-192,"width":98,"frameWidth":500,"height":98,"name":"圆环/圆2_0001","x":1607},{"y":753,"frameX":-169,"frameHeight":500,"frameY":-159,"width":166,"frameWidth":500,"height":164,"name":"圆环/圆2_0002","x":1005},{"y":383,"frameX":-67,"frameHeight":500,"frameY":-57,"width":370,"frameWidth":500,"height":368,"name":"圆环/圆2_0007","x":1005},{"width":500,"y":1,"height":500,"name":"圆环/圆2_0011","x":1},{"y":383,"frameX":-93,"frameHeight":500,"frameY":-83,"width":318,"frameWidth":500,"height":316,"name":"圆环/圆2_0005","x":1727},{"y":701,"frameX":-113,"frameHeight":500,"frameY":-103,"width":278,"frameWidth":500,"height":276,"name":"圆环/圆2_0004","x":1727},{"width":500,"y":503,"height":500,"name":"圆环/圆2_0000","x":503},{"y":731,"frameX":-138,"frameHeight":500,"frameY":-128,"width":228,"frameWidth":500,"height":226,"name":"圆环/圆2_0003","x":1377},{"width":500,"y":503,"height":500,"name":"圆环/圆2_0009","x":1}]}