{"name":"db_sheep_idle","imagePath":"db_sheep_idle_tex_1.png","SubTexture":[{"name":"db_sheep_idle0015","x":2,"height":540,"y":1086,"width":540},{"name":"db_sheep_idle0019","x":544,"height":540,"y":544,"width":540},{"name":"db_sheep_idle0009","x":1086,"height":540,"y":544,"width":540},{"name":"db_sheep_idle0010","x":544,"height":540,"y":1086,"width":540},{"name":"db_sheep_idle0001","x":1086,"height":540,"y":1086,"width":540},{"name":"db_sheep_idle0012","x":2,"height":540,"y":2,"width":540},{"name":"db_sheep_idle0016","x":1086,"height":540,"y":2,"width":540},{"name":"db_sheep_idle0007","x":2,"height":540,"y":544,"width":540},{"name":"db_sheep_idle0006","x":544,"height":540,"y":2,"width":540}],"height":2048,"width":2048}