{"SubTexture":[{"y":2,"frameX":0,"frameHeight":813,"frameY":-5,"width":540,"frameWidth":540,"height":808,"name":"huxi0008","x":2},{"y":810,"frameX":0,"frameHeight":813,"frameY":-7,"width":540,"frameWidth":540,"height":806,"name":"huxi0007","x":544},{"y":2,"frameX":0,"frameHeight":813,"frameY":-7,"width":540,"frameWidth":540,"height":806,"name":"huxi0005","x":544},{"y":2,"frameX":0,"frameHeight":813,"frameY":-8,"width":540,"frameWidth":540,"height":805,"name":"huxi0006","x":1086},{"y":812,"frameX":0,"frameHeight":813,"frameY":-5,"width":540,"frameWidth":540,"height":808,"name":"huxi0004","x":2}],"width":2048,"imagePath":"db_idle_tex_1.png","height":2048,"name":"db_idle"}