{"frameRate":24,"name":"db_no_like_cat","version":"5.5","compatibleVersion":"5.5","armature":[{"type":"Sheet","frameRate":24,"name":"db_no_like_cat","aabb":{"x":-263,"y":-378.5,"width":526,"height":757},"bone":[{"name":"root"}],"slot":[{"displayIndex":19,"name":"sheetSlot","parent":"root"}],"skin":[{"slot":[{"name":"sheetSlot","display":[{"name":"Idlc0001"},{"name":"Idlc0002"},{"name":"Idlc0003"},{"name":"Idlc0004"},{"name":"Idlc0005"},{"name":"Idlc0006"},{"name":"Idlc0007"},{"name":"Idlc0008"},{"name":"Idlc0009"},{"name":"Idlc0010"},{"name":"Idlc0011"},{"name":"Idlc0012"},{"name":"Idlc0013"},{"name":"Idlc0014"},{"name":"Idlc0015"},{"name":"Idlc0016"},{"name":"Idlc0017"},{"name":"Idlc0018"},{"name":"Idlc0019"},{"name":"Idlc0020"}]}]}],"animation":[{"duration":20,"playTimes":0,"name":"db_no_like_cat","slot":[{"name":"sheetSlot","displayFrame":[{},{"value":1},{"value":2},{"value":3},{"value":4},{"value":5},{"value":6},{"value":7},{"value":8},{"value":9},{"value":10},{"value":11},{"value":12},{"value":13},{"value":14},{"value":15},{"value":16},{"value":17},{"value":18},{"value":19}]}]}],"defaultActions":[{"gotoAndPlay":"db_no_like_cat"}]}]}