{"frameRate":24,"name":"snow2","version":"5.5","compatibleVersion":"5.5","armature":[{"type":"Sheet","frameRate":12,"name":"snow2","aabb":{"x":-225,"y":-159.5,"width":450,"height":319},"bone":[{"name":"root"}],"slot":[{"displayIndex":13,"name":"sheetSlot","parent":"root"}],"skin":[{"slot":[{"name":"sheetSlot","display":[{"name":"snow2_1"},{"name":"snow2_3"},{"name":"snow2_5"},{"name":"snow2_7"},{"name":"snow2_9"},{"name":"snow2_11"},{"name":"snow2_13"},{"name":"snow2_15"},{"name":"snow2_17"},{"name":"snow2_19"},{"name":"snow2_21"},{"name":"snow2_23"},{"name":"snow2_25"},{"name":"snow2_27"},{"name":"snow2_29"},{"name":"snow2_31"},{"name":"snow2_33"},{"name":"snow2_35"}]}]}],"animation":[{"duration":18,"playTimes":0,"name":"snow2","slot":[{"name":"sheetSlot","displayFrame":[{},{"value":1},{"value":2},{"value":3},{"value":4},{"value":5},{"value":6},{"value":7},{"value":8},{"value":9},{"value":10},{"value":11},{"value":12},{"value":13},{"value":14},{"value":15},{"value":16},{"value":17}]}]}],"defaultActions":[{"gotoAndPlay":"snow2"}]}]}