{"name":"db_sheep_catch","imagePath":"db_sheep_catch_tex.png","SubTexture":[{"name":"db_sheep_catch14","x":936,"height":176,"frameWidth":480,"y":2104,"frameY":-300,"frameHeight":477,"frameX":0,"width":463},{"name":"db_sheep_catch16","x":471,"height":180,"frameWidth":480,"y":1793,"frameY":-296,"frameHeight":477,"frameX":0,"width":468},{"name":"db_sheep_catch15","x":1417,"height":179,"frameWidth":480,"y":1195,"frameY":-297,"frameHeight":477,"frameX":0,"width":480},{"name":"db_sheep_catch09","x":953,"height":474,"frameWidth":480,"y":477,"frameY":-2,"frameHeight":477,"frameX":0,"width":474},{"name":"db_sheep_catch18","x":1411,"height":180,"frameWidth":480,"y":1740,"frameY":-296,"frameHeight":477,"frameX":0,"width":468},{"name":"db_sheep_catch27","x":1,"height":180,"frameWidth":480,"y":1429,"frameY":-296,"frameHeight":477,"frameX":0,"width":468},{"name":"db_sheep_catch19","x":941,"height":180,"frameWidth":480,"y":1922,"frameY":-296,"frameHeight":477,"frameX":0,"width":468},{"name":"db_sheep_catch22","x":471,"height":180,"frameWidth":480,"y":1611,"frameY":-296,"frameHeight":477,"frameX":0,"width":468},{"name":"db_sheep_catch06","x":1,"height":474,"frameWidth":480,"y":953,"frameY":-2,"frameHeight":477,"frameX":0,"width":474},{"name":"db_sheep_catch30","x":941,"height":180,"frameWidth":480,"y":1740,"frameY":-296,"frameHeight":477,"frameX":0,"width":468},{"name":"db_sheep_catch24","x":1411,"height":180,"frameWidth":480,"y":1922,"frameY":-296,"frameHeight":477,"frameX":0,"width":468},{"name":"db_sheep_catch03","x":477,"height":474,"frameWidth":480,"y":953,"frameY":-2,"frameHeight":477,"frameX":0,"width":474},{"name":"db_sheep_catch08","x":959,"height":474,"frameWidth":480,"y":1,"frameY":-2,"frameHeight":477,"frameX":0,"width":474},{"name":"db_sheep_catch07","x":1,"height":474,"frameWidth":480,"y":477,"frameY":-2,"frameHeight":477,"frameX":0,"width":474},{"name":"db_sheep_catch02","x":1429,"height":474,"frameWidth":480,"y":477,"frameY":-2,"frameHeight":477,"frameX":0,"width":474},{"name":"db_sheep_catch11","x":953,"height":390,"frameWidth":480,"y":953,"frameY":-86,"frameHeight":477,"frameX":0,"width":462},{"name":"db_sheep_catch26","x":1,"height":180,"frameWidth":480,"y":1975,"frameY":-296,"frameHeight":477,"frameX":0,"width":468},{"name":"db_sheep_catch04","x":1,"height":474,"frameWidth":480,"y":1,"frameY":-2,"frameHeight":477,"frameX":-1,"width":477},{"name":"db_sheep_catch29","x":953,"height":180,"frameWidth":480,"y":1376,"frameY":-296,"frameHeight":477,"frameX":0,"width":468},{"name":"db_sheep_catch17","x":1411,"height":180,"frameWidth":480,"y":1558,"frameY":-296,"frameHeight":477,"frameX":0,"width":468},{"name":"db_sheep_catch01","x":477,"height":474,"frameWidth":480,"y":477,"frameY":-2,"frameHeight":477,"frameX":0,"width":474},{"name":"db_sheep_catch28","x":471,"height":180,"frameWidth":480,"y":1429,"frameY":-296,"frameHeight":477,"frameX":0,"width":468},{"name":"db_sheep_catch10","x":1435,"height":474,"frameWidth":480,"y":1,"frameY":-2,"frameHeight":477,"frameX":0,"width":474},{"name":"db_sheep_catch12","x":1417,"height":240,"frameWidth":480,"y":953,"frameY":-236,"frameHeight":477,"frameX":0,"width":463},{"name":"db_sheep_catch23","x":1423,"height":180,"frameWidth":480,"y":1376,"frameY":-296,"frameHeight":477,"frameX":0,"width":468},{"name":"db_sheep_catch05","x":480,"height":474,"frameWidth":480,"y":1,"frameY":-2,"frameHeight":477,"frameX":0,"width":477},{"name":"db_sheep_catch21","x":1,"height":180,"frameWidth":480,"y":1611,"frameY":-296,"frameHeight":477,"frameX":0,"width":468},{"name":"db_sheep_catch25","x":1,"height":180,"frameWidth":480,"y":1793,"frameY":-296,"frameHeight":477,"frameX":0,"width":468},{"name":"db_sheep_catch20","x":941,"height":180,"frameWidth":480,"y":1558,"frameY":-296,"frameHeight":477,"frameX":0,"width":468},{"name":"db_sheep_catch13","x":471,"height":180,"frameWidth":480,"y":1975,"frameY":-296,"frameHeight":477,"frameX":0,"width":463}],"height":4096,"width":2048}